arcgis_marketplace/__init__.py
arcgis_marketplace/admin.py
arcgis_marketplace/apps.py
arcgis_marketplace/factories.py
arcgis_marketplace/fields.py
arcgis_marketplace/managers.py
arcgis_marketplace/models.py
arcgis_marketplace/pipeline.py
arcgis_marketplace/settings.py
arcgis_marketplace/tasks.py
arcgis_marketplace/urls.py
arcgis_marketplace/utils.py
arcgis_marketplace/validators.py
arcgis_marketplace/api/__init__.py
arcgis_marketplace/api/decorators.py
arcgis_marketplace/api/exceptions.py
arcgis_marketplace/api/fields.py
arcgis_marketplace/api/mixins.py
arcgis_marketplace/api/pagination.py
arcgis_marketplace/api/permissions.py
arcgis_marketplace/api/urls.py
arcgis_marketplace/api/v1/__init__.py
arcgis_marketplace/api/v1/serializers.py
arcgis_marketplace/api/v1/urls.py
arcgis_marketplace/api/v1/views.py
arcgis_marketplace/locale/es/LC_MESSAGES/django.mo
arcgis_marketplace/locale/es/LC_MESSAGES/django.po
arcgis_marketplace/migrations/0001_initial.py
arcgis_marketplace/migrations/0002_auto_20170813_0747.py
arcgis_marketplace/migrations/__init__.py
arcgis_marketplace/signals/__init__.py
arcgis_marketplace/signals/loggers.py
arcgis_marketplace/templates/arcgis_marketplace/index.html
django_arcgis_marketplace-0.0.13.dist-info/DESCRIPTION.rst
django_arcgis_marketplace-0.0.13.dist-info/METADATA
django_arcgis_marketplace-0.0.13.dist-info/RECORD
django_arcgis_marketplace-0.0.13.dist-info/WHEEL
django_arcgis_marketplace-0.0.13.dist-info/metadata.json
django_arcgis_marketplace-0.0.13.dist-info/top_level.txt
