Metadata-Version: 2.0
Name: django-arcgis-marketplace
Version: 0.0.13
Summary: Arcgis marketplace app.
Home-page: https://github.com/flavors/arcgis-marketplace/
Author: mongkok
Author-email: dani.pyc@gmail.com
License: MIT
Platform: UNKNOWN
Classifier: Development Status :: 1 - Planning
Classifier: Environment :: Web Environment
Classifier: Intended Audience :: Developers
Classifier: License :: OSI Approved :: MIT License
Classifier: Operating System :: OS Independent
Classifier: Programming Language :: Python
Classifier: Programming Language :: Python :: 3
Classifier: Programming Language :: Python :: 3.5
Classifier: Programming Language :: Python :: 3.6
Classifier: Framework :: Django
Requires-Dist: arcgis-sdk (>=0.0.12)
Requires-Dist: celery (>=4.0.2)
Requires-Dist: django-core-flavor (>=0.0.21)
Requires-Dist: django-filter (>=1.0.2)
Requires-Dist: django-orders-flavor (>=0.0.7)
Requires-Dist: django-polymorphic (>=1.3)
Requires-Dist: django-taggit (>=0.22.1)
Requires-Dist: django-taggit-serializer (>=0.1.5)
Requires-Dist: djangorestframework (>=3.5.0)
Requires-Dist: Pillow (>=4.1.1)
Requires-Dist: psycopg2 (>=2.6.2)
Requires-Dist: social-auth-app-django (>=1.2.0)
Requires-Dist: sorl-thumbnail (>=12.3)
